{"nodes": [{"id": "project_brief_doc", "label": "Project Brief", "file_type": "document", "source_file": "PROJECT_BRIEF.md", "source_location": null, "source_url": null, "captured_at": null, "author": "Ronnie / Quantum Neuro Creations", "contributor": null}, {"id": "android_twa", "label": "Android TWA (Trusted Web Activity)", "file_type": "concept", "source_file": "PROJECT_BRIEF.md", "source_location": null, "source_url": null, "captured_at": null, "author": null, "contributor": null}, {"id": "quantumcube_app_domain", "label": "quantumcube.app Domain", "file_type": "concept", "source_file": "PROJECT_BRIEF.md", "source_location": null, "source_url": null, "captured_at": null, "author": null, "contributor": null}], "edges": [{"source": "project_brief_doc", "target": "brief_archive_doc", "relation": "references", "confidence": "EXTRACTED", "confidence_score": 1.0, "source_file": "PROJECT_BRIEF.md", "source_location": "Archive note", "weight": 1.0}, {"source": "project_brief_doc", "target": "chat_kickoff_doc", "relation": "references", "confidence": "EXTRACTED", "confidence_score": 1.0, "source_file": "PROJECT_BRIEF.md", "source_location": "NEW CHAT section", "weight": 1.0}, {"source": "project_brief_doc", "target": "session_log_doc", "relation": "references", "confidence": "EXTRACTED", "confidence_score": 1.0, "source_file": "PROJECT_BRIEF.md", "source_location": "v42 update note", "weight": 1.0}, {"source": "android_twa", "target": "google_play_store", "relation": "conceptually_related_to", "confidence": "EXTRACTED", "confidence_score": 1.0, "source_file": "PROJECT_BRIEF.md", "source_location": "TWA references", "weight": 1.0}, {"source": "narrate_fn", "target": "elevenlabs_service", "relation": "calls", "confidence": "EXTRACTED", "confidence_score": 1.0, "source_file": "PROJECT_BRIEF.md", "source_location": "v44 narration audit session", "weight": 1.0}, {"source": "resend_events_fn", "target": "resend_service", "relation": "calls", "confidence": "EXTRACTED", "confidence_score": 1.0, "source_file": "PROJECT_BRIEF.md", "source_location": "v42 resend-events Edge Function", "weight": 1.0}, {"source": "resend_events_fn", "target": "sentry_service", "relation": "calls", "confidence": "EXTRACTED", "confidence_score": 1.0, "source_file": "PROJECT_BRIEF.md", "source_location": "v42 resend-events forwards to Sentry", "weight": 1.0}, {"source": "uptimerobot_service", "target": "narrate_fn", "relation": "conceptually_related_to", "confidence": "EXTRACTED", "confidence_score": 0.8, "source_file": "PROJECT_BRIEF.md", "source_location": "v42 UptimeRobot Narrate monitor", "weight": 0.7}], "hyperedges": []}